{"timestamp":"2020-12-13T09:56:00Z","data":[{"data_type":"pm10","value":"4.13","max":"5.00","min":"3.00","sd":"0.83"},{"data_type":"pm2.5","value":"4.13","max":"5.00","min":"3.00","sd":"0.83"},{"data_type":"pm1","value":"2.80","max":"3.00","min":"2.00","sd":"0.41"},{"data_type":"pm10","value":"3.33","max":"4.00","min":"2.00","sd":"0.72","sensor":2},{"data_type":"pm2.5","value":"3.20","max":"4.00","min":"2.00","sd":"0.77","sensor":2},{"data_type":"pm1","value":"2.87","max":"4.00","min":"2.00","sd":"0.52","sensor":2},{"data_type":"pm10","value":"686.00","max":"723.00","min":"645.00","sd":"27.42","sensor":3},{"data_type":"pm2.5","value":"183.40","max":"205.00","min":"159.00","sd":"16.39","sensor":3},{"data_type":"pm1","value":"27.00","max":"33.00","min":"22.00","sd":"3.76","sensor":3},{"data_type":"pm10","value":"1.47","max":"4.00","min":"0.00","sd":"1.77","sensor":4},{"data_type":"pm2.5","value":"0.00","max":"0.00","min":"0.00","sd":"0.00","sensor":4},{"data_type":"pm1","value":"0.00","max":"0.00","min":"0.00","sd":"0.00","sensor":4},{"data_type":"pm10","value":"368.80","max":"810.00","min":"0.00","sd":"368.82","sensor":5},{"data_type":"pm2.5","value":"197.73","max":"226.00","min":"172.00","sd":"15.23","sensor":5},{"data_type":"pm1","value":"13.20","max":"19.00","min":"8.00","sd":"4.30","sensor":5},{"data_type":"pm10","value":"0.87","max":"2.00","min":"0.00","sd":"0.99","sensor":6},{"data_type":"pm2.5","value":"0.40","max":"1.00","min":"0.00","sd":"0.51","sensor":6},{"data_type":"noise","value":"31.08","max":"40.52","min":"27.76","sd":"1.46"},{"data_type":"illuminance","value":"106.56","max":"108.00","min":"106.00","sd":"0.62"},{"data_type":"irradiance","value":"0.00","max":"0.00","min":"0.00","sd":"0.00"},{"data_type":"temperature","value":"28.02","max":"28.03","min":"28.00","sd":"0.01"},{"data_type":"humidity","value":"56.05","max":"56.13","min":"55.95","sd":"0.04"},{"data_type":"presure","value":"898.62","max":"898.65","min":"898.59","sd":"0.02"},{"data_type":"rain","value":"0.00","max":"0.00","min":"0.00","sd":"0.00"},{"data_type":"precipitation","value":"0.00","max":"0.00","min":"0.00","sd":"0.00"}]}
