{"timestamp":"2020-12-20T12:30:45Z","data":[{"data_type":"pm10","value":"32.20","max":"35.00","min":"29.00","sd":"2.08"},{"data_type":"pm2.5","value":"30.13","max":"31.00","min":"29.00","sd":"0.74"},{"data_type":"pm1","value":"20.53","max":"22.00","min":"19.00","sd":"0.74"},{"data_type":"pm10","value":"32.80","max":"39.00","min":"29.00","sd":"2.93","sensor":2},{"data_type":"pm2.5","value":"30.67","max":"34.00","min":"28.00","sd":"1.76","sensor":2},{"data_type":"pm1","value":"21.20","max":"22.00","min":"20.00","sd":"0.77","sensor":2},{"data_type":"pm10","value":"3944.60","max":"4053.00","min":"3873.00","sd":"57.28","sensor":3},{"data_type":"pm2.5","value":"1104.27","max":"1141.00","min":"1080.00","sd":"17.09","sensor":3},{"data_type":"pm1","value":"176.53","max":"186.00","min":"168.00","sd":"5.22","sensor":3},{"data_type":"pm10","value":"16.00","max":"28.00","min":"5.00","sd":"7.83","sensor":4},{"data_type":"pm2.5","value":"2.00","max":"4.00","min":"0.00","sd":"1.56","sensor":4},{"data_type":"pm1","value":"1.07","max":"2.00","min":"0.00","sd":"0.80","sensor":4},{"data_type":"pm10","value":"2037.07","max":"4320.00","min":"0.00","sd":"2035.55","sensor":5},{"data_type":"pm2.5","value":"1133.40","max":"1206.00","min":"1036.00","sd":"49.88","sensor":5},{"data_type":"pm1","value":"183.47","max":"234.00","min":"148.00","sd":"28.53","sensor":5},{"data_type":"pm10","value":"8.80","max":"15.00","min":"4.00","sd":"3.34","sensor":6},{"data_type":"pm2.5","value":"1.67","max":"3.00","min":"0.00","sd":"0.82","sensor":6},{"data_type":"noise","value":"35.85","max":"52.71","min":"31.82","sd":"1.96"},{"data_type":"illuminance","value":"1574.30","max":"1598.00","min":"1558.00","sd":"14.14"},{"data_type":"irradiance","value":"6906.91","max":"7068.66","min":"6837.58","sd":"54.72"},{"data_type":"temperature","value":"24.60","max":"24.63","min":"24.58","sd":"0.09"},{"data_type":"humidity","value":"63.34","max":"63.63","min":"62.89","sd":"0.37"},{"data_type":"presure","value":"908.42","max":"908.47","min":"908.39","sd":"0.12"},{"data_type":"rain","value":"0.00","max":"0.00","min":"0.00","sd":"0.00"},{"data_type":"precipitation","value":"0.00","max":"0.00","min":"0.00","sd":"0.00"},{"data_type":"voltage","value":"4.24","max":"4.28","min":"4.20","sd":"0.15"},{"data_type":"batery","value":"4.16","max":"4.17","min":"4.16","sd":"0.05"},{"data_type":"panel","value":"4.42","max":"4.56","min":"1.12","sd":"0.63"}]}
