{"timestamp":"2020-12-14T05:50:53Z","data":[{"data_type":"pm2.5","value":"6.27","max":"8.00","min":"5.00","sd":"0.88"},{"data_type":"pm1","value":"5.20","max":"6.00","min":"4.00","sd":"0.77"},{"data_type":"pm10","value":"0.00","max":"0.00","min":"0.00","sd":"0.00","sensor":5},{"data_type":"pm2.5","value":"0.00","max":"0.00","min":"0.00","sd":"0.00","sensor":6},{"data_type":"noise","value":"30.10","max":"34.72","min":"27.76","sd":"1.09"},{"data_type":"illuminance","value":"97.78","max":"98.00","min":"97.00","sd":"0.65"},{"data_type":"irradiance","value":"0.00","max":"0.00","min":"0.00","sd":"0.00"},{"data_type":"temperature","value":"27.41","max":"27.42","min":"27.41","sd":"0.00"},{"data_type":"humidity","value":"58.32","max":"58.40","min":"58.23","sd":"0.05"},{"data_type":"presure","value":"899.31","max":"899.34","min":"899.29","sd":"0.02"},{"data_type":"rain","value":"0.00","max":"0.00","min":"0.00","sd":"0.00"},{"data_type":"precipitation","value":"0.00","max":"0.00","min":"0.00","sd":"0.00"}]}
