{"timestamp":"2020-12-16T08:05:59Z","data":[{"data_type":"pm10","value":"48.40","max":"50.00","min":"45.00","sd":"1.68"},{"data_type":"pm2.5","value":"40.60","max":"43.00","min":"38.00","sd":"1.35"},{"data_type":"pm1","value":"26.73","max":"28.00","min":"25.00","sd":"0.70"},{"data_type":"pm10","value":"44.00","max":"45.00","min":"41.00","sd":"1.25","sensor":2},{"data_type":"pm2.5","value":"38.07","max":"39.00","min":"36.00","sd":"0.80","sensor":2},{"data_type":"pm1","value":"27.00","max":"28.00","min":"26.00","sd":"0.65","sensor":2},{"data_type":"pm10","value":"5877.00","max":"6114.00","min":"5640.00","sd":"151.69","sensor":3},{"data_type":"pm2.5","value":"1626.60","max":"1713.00","min":"1544.00","sd":"47.26","sensor":3},{"data_type":"pm1","value":"271.40","max":"312.00","min":"234.00","sd":"27.08","sensor":3},{"data_type":"pm10","value":"34.33","max":"41.00","min":"25.00","sd":"4.10","sensor":4},{"data_type":"pm2.5","value":"2.33","max":"5.00","min":"0.00","sd":"1.40","sensor":4},{"data_type":"pm1","value":"1.47","max":"3.00","min":"0.00","sd":"1.06","sensor":4},{"data_type":"pm10","value":"2819.33","max":"5781.00","min":"0.00","sd":"2819.08","sensor":5},{"data_type":"pm2.5","value":"1580.47","max":"1635.00","min":"1506.00","sd":"38.51","sensor":5},{"data_type":"pm1","value":"243.47","max":"278.00","min":"222.00","sd":"15.39","sensor":5},{"data_type":"pm10","value":"11.40","max":"17.00","min":"4.00","sd":"4.07","sensor":6},{"data_type":"pm2.5","value":"0.60","max":"1.00","min":"0.00","sd":"0.51","sensor":6},{"data_type":"noise","value":"33.82","max":"38.20","min":"29.50","sd":"1.28"},{"data_type":"illuminance","value":"86.94","max":"88.00","min":"85.00","sd":"0.94"},{"data_type":"irradiance","value":"0.00","max":"0.00","min":"0.00","sd":"0.00"},{"data_type":"temperature","value":"24.00","max":"24.01","min":"24.00","sd":"0.01"},{"data_type":"humidity","value":"71.68","max":"72.01","min":"71.54","sd":"0.16"},{"data_type":"presure","value":"906.70","max":"906.73","min":"906.66","sd":"0.02"},{"data_type":"rain","value":"0.00","max":"0.00","min":"0.00","sd":"0.00"},{"data_type":"precipitation","value":"0.00","max":"0.00","min":"0.00","sd":"0.00"}]}
