{"timestamp":"2020-12-15T12:34:58Z","data":[{"data_type":"pm10","value":"20.07","max":"23.00","min":"17.00","sd":"1.53"},{"data_type":"pm2.5","value":"19.87","max":"22.00","min":"17.00","sd":"1.41"},{"data_type":"pm1","value":"14.67","max":"16.00","min":"12.00","sd":"1.18"},{"data_type":"pm10","value":"18.60","max":"20.00","min":"17.00","sd":"1.06","sensor":2},{"data_type":"pm2.5","value":"18.47","max":"20.00","min":"17.00","sd":"0.92","sensor":2},{"data_type":"pm1","value":"14.53","max":"16.00","min":"13.00","sd":"0.74","sensor":2},{"data_type":"pm10","value":"2709.00","max":"2949.00","min":"2454.00","sd":"172.17","sensor":3},{"data_type":"pm2.5","value":"756.93","max":"822.00","min":"688.00","sd":"47.63","sensor":3},{"data_type":"pm1","value":"106.40","max":"121.00","min":"91.00","sd":"7.61","sensor":3},{"data_type":"pm10","value":"5.73","max":"11.00","min":"2.00","sd":"3.03","sensor":4},{"data_type":"pm2.5","value":"0.13","max":"1.00","min":"0.00","sd":"0.35","sensor":4},{"data_type":"pm1","value":"0.13","max":"1.00","min":"0.00","sd":"0.35","sensor":4},{"data_type":"pm10","value":"1347.30","max":"2850.00","min":"0.00","sd":"1347.32","sensor":5},{"data_type":"pm2.5","value":"722.40","max":"773.00","min":"676.00","sd":"24.05","sensor":5},{"data_type":"pm1","value":"90.27","max":"114.00","min":"62.00","sd":"16.54","sensor":5},{"data_type":"pm10","value":"5.47","max":"10.00","min":"2.00","sd":"2.88","sensor":6},{"data_type":"pm2.5","value":"0.40","max":"1.00","min":"0.00","sd":"0.51","sensor":6},{"data_type":"noise","value":"35.82","max":"45.74","min":"31.24","sd":"1.84"},{"data_type":"illuminance","value":"881.72","max":"894.00","min":"881.00","sd":"3.06"},{"data_type":"irradiance","value":"2262.30","max":"2262.30","min":"2262.30","sd":"0.00"},{"data_type":"temperature","value":"24.45","max":"24.46","min":"24.44","sd":"0.01"},{"data_type":"humidity","value":"62.97","max":"63.33","min":"62.55","sd":"0.26"},{"data_type":"presure","value":"909.46","max":"909.49","min":"909.45","sd":"0.01"},{"data_type":"rain","value":"0.00","max":"0.00","min":"0.00","sd":"0.00"},{"data_type":"precipitation","value":"0.00","max":"0.00","min":"0.00","sd":"0.00"},{"data_type":"voltage","value":"5.07","max":"5.07","min":"5.07","sd":"0.05"},{"data_type":"batery","value":"4.31","max":"4.31","min":"4.31","sd":"0.00"},{"data_type":"panel","value":"5.32","max":"5.32","min":"5.31","sd":"0.07"}]}
