{"timestamp":"2020-12-14T17:35:37Z","data":[{"data_type":"pm10","value":"18.53","max":"21.00","min":"17.00","sd":"0.92"},{"data_type":"pm2.5","value":"18.53","max":"21.00","min":"17.00","sd":"0.92"},{"data_type":"pm1","value":"14.00","max":"16.00","min":"13.00","sd":"0.76"},{"data_type":"pm10","value":"22.53","max":"25.00","min":"20.00","sd":"1.46","sensor":2},{"data_type":"pm2.5","value":"21.53","max":"23.00","min":"20.00","sd":"0.99","sensor":2},{"data_type":"pm1","value":"15.93","max":"17.00","min":"15.00","sd":"0.70","sensor":2},{"data_type":"pm10","value":"2574.20","max":"2856.00","min":"2424.00","sd":"121.70","sensor":3},{"data_type":"pm2.5","value":"711.33","max":"796.00","min":"675.00","sd":"32.97","sensor":3},{"data_type":"pm1","value":"96.47","max":"121.00","min":"77.00","sd":"10.25","sensor":3},{"data_type":"pm10","value":"1.93","max":"4.00","min":"0.00","sd":"1.10","sensor":4},{"data_type":"pm2.5","value":"0.00","max":"0.00","min":"0.00","sd":"0.00","sensor":4},{"data_type":"pm1","value":"0.00","max":"0.00","min":"0.00","sd":"0.00","sensor":4},{"data_type":"pm10","value":"1453.60","max":"3024.00","min":"0.00","sd":"1453.01","sensor":5},{"data_type":"pm2.5","value":"800.27","max":"865.00","min":"753.00","sd":"30.68","sensor":5},{"data_type":"pm1","value":"125.07","max":"150.00","min":"96.00","sd":"13.87","sensor":5},{"data_type":"pm10","value":"6.33","max":"12.00","min":"2.00","sd":"3.15","sensor":6},{"data_type":"pm2.5","value":"1.80","max":"4.00","min":"0.00","sd":"1.37","sensor":6},{"data_type":"noise","value":"43.29","max":"96.79","min":"35.30","sd":"6.20"},{"data_type":"illuminance","value":"2544.56","max":"2777.00","min":"2287.00","sd":"193.38"},{"data_type":"irradiance","value":"18039.59","max":"21949.89","min":"14000.91","sd":"2951.56"},{"data_type":"temperature","value":"31.16","max":"31.21","min":"31.11","sd":"0.03"},{"data_type":"humidity","value":"42.01","max":"42.23","min":"41.77","sd":"0.10"},{"data_type":"presure","value":"907.86","max":"907.91","min":"907.83","sd":"0.02"},{"data_type":"rain","value":"0.00","max":"0.00","min":"0.00","sd":"0.00"},{"data_type":"precipitation","value":"0.00","max":"0.00","min":"0.00","sd":"0.00"}]}
