{"timestamp":"2020-12-22T19:45:31Z","data":[{"data_type":"noise","value":"43.27","max":"79.39","min":"37.62","sd":"3.50"},{"data_type":"illuminance","value":"1272.50","max":"1298.00","min":"1271.00","sd":"2.82"},{"data_type":"irradiance","value":"4107.48","max":"4157.11","min":"4064.69","sd":"31.80"},{"data_type":"temperature","value":"29.61","max":"29.61","min":"29.59","sd":"0.08"},{"data_type":"humidity","value":"50.96","max":"51.01","min":"50.88","sd":"0.20"},{"data_type":"presure","value":"906.41","max":"906.44","min":"906.36","sd":"0.02"},{"data_type":"rain","value":"0.00","max":"0.00","min":"0.00","sd":"0.00"},{"data_type":"precipitation","value":"0.00","max":"0.00","min":"0.00","sd":"0.00"},{"data_type":"voltage","value":"5.04","max":"5.05","min":"5.03","sd":"0.09"},{"data_type":"batery","value":"4.36","max":"4.36","min":"4.36","sd":"0.00"},{"data_type":"panel","value":"5.30","max":"5.31","min":"5.28","sd":"0.09"}]}
