{"timestamp":"2020-12-13T05:33:10Z","data":[{"data_type":"pm10","value":"6.13","max":"7.00","min":"5.00","sd":"0.74"},{"data_type":"pm2.5","value":"6.07","max":"7.00","min":"5.00","sd":"0.70"},{"data_type":"pm1","value":"4.27","max":"5.00","min":"3.00","sd":"0.88"},{"data_type":"pm10","value":"4.40","max":"5.00","min":"4.00","sd":"0.51","sensor":2},{"data_type":"pm2.5","value":"4.40","max":"5.00","min":"4.00","sd":"0.51","sensor":2},{"data_type":"pm1","value":"4.13","max":"5.00","min":"3.00","sd":"0.52","sensor":2},{"data_type":"pm10","value":"887.80","max":"1038.00","min":"684.00","sd":"135.85","sensor":3},{"data_type":"pm2.5","value":"244.47","max":"283.00","min":"191.00","sd":"34.42","sensor":3},{"data_type":"pm1","value":"39.20","max":"47.00","min":"32.00","sd":"3.71","sensor":3},{"data_type":"pm10","value":"2.20","max":"4.00","min":"1.00","sd":"1.01","sensor":4},{"data_type":"pm2.5","value":"0.00","max":"0.00","min":"0.00","sd":"0.00","sensor":4},{"data_type":"pm1","value":"0.00","max":"0.00","min":"0.00","sd":"0.00","sensor":4},{"data_type":"pm10","value":"454.40","max":"960.00","min":"0.00","sd":"454.42","sensor":5},{"data_type":"pm2.5","value":"235.07","max":"262.00","min":"202.00","sd":"18.00","sensor":5},{"data_type":"pm1","value":"18.20","max":"26.00","min":"11.00","sd":"3.99","sensor":5},{"data_type":"pm10","value":"0.27","max":"1.00","min":"0.00","sd":"0.46","sensor":6},{"data_type":"pm2.5","value":"0.00","max":"0.00","min":"0.00","sd":"0.00","sensor":6},{"data_type":"noise","value":"30.89","max":"37.04","min":"28.34","sd":"1.14"},{"data_type":"illuminance","value":"103.94","max":"104.00","min":"103.00","sd":"0.24"},{"data_type":"irradiance","value":"0.00","max":"0.00","min":"0.00","sd":"0.00"},{"data_type":"temperature","value":"27.09","max":"27.10","min":"27.08","sd":"0.00"},{"data_type":"humidity","value":"57.53","max":"57.60","min":"57.42","sd":"0.05"},{"data_type":"presure","value":"898.65","max":"898.68","min":"898.63","sd":"0.01"},{"data_type":"rain","value":"0.00","max":"0.00","min":"0.00","sd":"0.00"},{"data_type":"precipitation","value":"0.00","max":"0.00","min":"0.00","sd":"0.00"}]}
