{"timestamp":"2020-12-22T11:58:01Z","data":[{"data_type":"pm10","value":"28.50","max":"33.00","min":"25.00","sd":"1.50"},{"data_type":"pm2.5","value":"27.33","max":"29.00","min":"25.00","sd":"1.02"},{"data_type":"pm1","value":"19.60","max":"20.00","min":"18.00","sd":"0.75"},{"data_type":"pm10","value":"25.87","max":"32.00","min":"21.00","sd":"3.58","sensor":2},{"data_type":"pm2.5","value":"25.20","max":"31.00","min":"20.00","sd":"3.32","sensor":2},{"data_type":"pm1","value":"20.27","max":"23.00","min":"17.00","sd":"1.29","sensor":2},{"data_type":"pm10","value":"3686.00","max":"3828.00","min":"3501.00","sd":"99.22","sensor":3},{"data_type":"pm2.5","value":"1016.73","max":"1044.00","min":"977.00","sd":"20.36","sensor":3},{"data_type":"pm1","value":"142.13","max":"163.00","min":"133.00","sd":"9.69","sensor":3},{"data_type":"pm10","value":"12.80","max":"17.00","min":"9.00","sd":"2.40","sensor":4},{"data_type":"pm2.5","value":"1.67","max":"5.00","min":"1.00","sd":"1.40","sensor":4},{"data_type":"pm1","value":"1.07","max":"5.00","min":"0.00","sd":"1.67","sensor":4},{"data_type":"pm10","value":"1814.23","max":"4653.00","min":"0.00","sd":"1813.83","sensor":5},{"data_type":"pm2.5","value":"1007.53","max":"1270.00","min":"860.00","sd":"117.51","sensor":5},{"data_type":"pm1","value":"122.00","max":"160.00","min":"86.00","sd":"23.70","sensor":5},{"data_type":"pm10","value":"4.07","max":"8.00","min":"1.00","sd":"1.67","sensor":6},{"data_type":"pm2.5","value":"0.47","max":"1.00","min":"0.00","sd":"0.52","sensor":6},{"data_type":"noise","value":"39.29","max":"61.41","min":"32.98","sd":"2.47"},{"data_type":"illuminance","value":"831.00","max":"831.00","min":"831.00","sd":"0.00"},{"data_type":"irradiance","value":"1848.93","max":"1892.58","min":"1846.36","sd":"10.89"},{"data_type":"temperature","value":"24.53","max":"24.54","min":"24.52","sd":"0.01"},{"data_type":"humidity","value":"70.70","max":"70.78","min":"70.57","sd":"0.06"},{"data_type":"presure","value":"909.70","max":"909.72","min":"909.67","sd":"0.01"},{"data_type":"rain","value":"0.00","max":"0.00","min":"0.00","sd":"0.00"},{"data_type":"precipitation","value":"0.00","max":"0.00","min":"0.00","sd":"0.00"},{"data_type":"voltage","value":"4.78","max":"4.93","min":"4.62","sd":"0.30"},{"data_type":"batery","value":"4.31","max":"4.31","min":"4.30","sd":"0.04"},{"data_type":"panel","value":"5.03","max":"5.18","min":"4.87","sd":"0.31"}]}
