{"timestamp":"2020-12-15T01:47:29Z","data":[{"data_type":"pm10","value":"30.07","max":"35.00","min":"28.00","sd":"1.32"},{"data_type":"pm2.5","value":"29.40","max":"32.00","min":"28.00","sd":"0.97"},{"data_type":"pm1","value":"20.24","max":"21.00","min":"19.00","sd":"0.69"},{"data_type":"pm10","value":"32.90","max":"37.00","min":"30.00","sd":"1.36","sensor":2},{"data_type":"pm2.5","value":"30.47","max":"32.00","min":"29.00","sd":"1.01","sensor":2},{"data_type":"pm1","value":"22.16","max":"23.00","min":"20.00","sd":"1.01","sensor":2},{"data_type":"pm10","value":"3779.40","max":"3957.00","min":"3630.00","sd":"79.49","sensor":3},{"data_type":"pm2.5","value":"1040.60","max":"1060.00","min":"1018.00","sd":"12.21","sensor":3},{"data_type":"pm1","value":"167.87","max":"186.00","min":"150.00","sd":"10.83","sensor":3},{"data_type":"pm10","value":"17.47","max":"32.00","min":"6.00","sd":"8.18","sensor":4},{"data_type":"pm2.5","value":"0.27","max":"1.00","min":"0.00","sd":"0.46","sensor":4},{"data_type":"pm1","value":"0.27","max":"1.00","min":"0.00","sd":"0.46","sensor":4},{"data_type":"pm10","value":"2145.90","max":"4560.00","min":"1.00","sd":"2144.52","sensor":5},{"data_type":"pm2.5","value":"1168.27","max":"1238.00","min":"1085.00","sd":"49.64","sensor":5},{"data_type":"pm1","value":"187.47","max":"212.00","min":"158.00","sd":"16.66","sensor":5},{"data_type":"pm10","value":"7.53","max":"12.00","min":"5.00","sd":"2.39","sensor":6},{"data_type":"pm2.5","value":"2.80","max":"5.00","min":"1.00","sd":"1.82","sensor":6},{"data_type":"noise","value":"40.89","max":"54.45","min":"31.82","sd":"3.60"},{"data_type":"illuminance","value":"56.67","max":"58.00","min":"56.00","sd":"0.77"},{"data_type":"irradiance","value":"0.00","max":"0.00","min":"0.00","sd":"0.00"},{"data_type":"temperature","value":"25.27","max":"25.29","min":"25.26","sd":"0.10"},{"data_type":"humidity","value":"67.59","max":"67.68","min":"67.49","sd":"0.23"},{"data_type":"presure","value":"909.35","max":"909.39","min":"909.32","sd":"0.02"},{"data_type":"rain","value":"0.00","max":"0.00","min":"0.00","sd":"0.00"},{"data_type":"precipitation","value":"0.00","max":"0.00","min":"0.00","sd":"0.00"},{"data_type":"voltage","value":"5.07","max":"5.07","min":"5.07","sd":"0.06"},{"data_type":"batery","value":"4.33","max":"4.33","min":"4.33","sd":"0.00"},{"data_type":"panel","value":"0.02","max":"0.03","min":"0.01","sd":"0.07"}]}
