{"timestamp":"2020-12-13T03:46:57Z","data":[{"data_type":"pm10","value":"11.13","max":"12.00","min":"10.00","sd":"0.74"},{"data_type":"pm2.5","value":"10.33","max":"12.00","min":"9.00","sd":"0.82"},{"data_type":"pm1","value":"7.47","max":"8.00","min":"7.00","sd":"0.52"},{"data_type":"pm10","value":"8.60","max":"11.00","min":"7.00","sd":"1.30","sensor":2},{"data_type":"pm2.5","value":"8.60","max":"11.00","min":"7.00","sd":"1.30","sensor":2},{"data_type":"pm1","value":"7.27","max":"9.00","min":"6.00","sd":"1.10","sensor":2},{"data_type":"pm10","value":"1445.00","max":"1554.00","min":"1302.00","sd":"83.10","sensor":3},{"data_type":"pm2.5","value":"396.87","max":"434.00","min":"358.00","sd":"23.92","sensor":3},{"data_type":"pm1","value":"58.73","max":"66.00","min":"50.00","sd":"4.76","sensor":3},{"data_type":"pm10","value":"2.80","max":"4.00","min":"1.00","sd":"1.21","sensor":4},{"data_type":"pm2.5","value":"1.13","max":"2.00","min":"0.00","sd":"0.92","sensor":4},{"data_type":"pm1","value":"0.53","max":"1.00","min":"0.00","sd":"0.52","sensor":4},{"data_type":"pm10","value":"703.80","max":"1524.00","min":"0.00","sd":"703.83","sensor":5},{"data_type":"pm2.5","value":"376.93","max":"426.00","min":"340.00","sd":"31.07","sensor":5},{"data_type":"pm1","value":"51.87","max":"72.00","min":"40.00","sd":"11.70","sensor":5},{"data_type":"pm10","value":"1.53","max":"3.00","min":"0.00","sd":"0.83","sensor":6},{"data_type":"pm2.5","value":"0.00","max":"0.00","min":"0.00","sd":"0.00","sensor":6},{"data_type":"noise","value":"36.91","max":"57.93","min":"29.50","sd":"3.11"},{"data_type":"illuminance","value":"134.61","max":"135.00","min":"134.00","sd":"0.50"},{"data_type":"irradiance","value":"0.00","max":"0.00","min":"0.00","sd":"0.00"},{"data_type":"temperature","value":"26.32","max":"26.32","min":"26.31","sd":"0.07"},{"data_type":"humidity","value":"64.91","max":"65.01","min":"64.84","sd":"0.05"},{"data_type":"presure","value":"899.85","max":"899.89","min":"899.82","sd":"0.02"},{"data_type":"rain","value":"0.00","max":"0.00","min":"0.00","sd":"0.00"},{"data_type":"precipitation","value":"0.00","max":"0.00","min":"0.00","sd":"0.00"}]}
