{"timestamp":"2020-12-22T15:17:08Z","data":[{"data_type":"pm10","value":"27.29","max":"101.03","min":"4.06","sd":"26.09"},{"data_type":"pm2.5","value":"7.09","max":"12.65","min":"3.97","sd":"2.07"},{"data_type":"pm1","value":"2.46","max":"3.63","min":"1.78","sd":"0.47"},{"data_type":"pm10","value":"23.78","max":"27.00","min":"19.00","sd":"3.07","sensor":2},{"data_type":"pm2.5","value":"21.67","max":"25.00","min":"17.00","sd":"3.00","sensor":2},{"data_type":"pm1","value":"14.44","max":"17.00","min":"13.00","sd":"1.42","sensor":2},{"data_type":"pm10","value":"1521.83","max":"3345.00","min":"2.00","sd":"1519.20","sensor":5},{"data_type":"pm2.5","value":"761.44","max":"875.00","min":"669.00","sd":"73.55","sensor":5},{"data_type":"pm1","value":"118.00","max":"152.00","min":"85.00","sd":"25.82","sensor":5},{"data_type":"pm10","value":"11.22","max":"16.00","min":"4.00","sd":"4.60","sensor":6},{"data_type":"pm2.5","value":"2.67","max":"4.00","min":"2.00","sd":"0.71","sensor":6},{"data_type":"pm10","value":"1.95","max":"14.00","min":"0.00","sd":"2.82","sensor":7},{"data_type":"pm2.5","value":"28.15","max":"41.00","min":"18.00","sd":"5.88","sensor":7},{"data_type":"pm1","value":"3.13","max":"7.00","min":"0.00","sd":"1.66","sensor":7},{"data_type":"pm10","value":"1.05","max":"3.00","min":"0.00","sd":"0.89","sensor":8},{"data_type":"pm2.5","value":"0.37","max":"2.00","min":"0.00","sd":"0.59","sensor":8},{"data_type":"pm1","value":"0.32","max":"2.00","min":"0.00","sd":"0.57","sensor":8},{"data_type":"pm10","value":"0.28","max":"2.00","min":"0.00","sd":"0.56","sensor":9},{"data_type":"pm2.5","value":"0.03","max":"1.00","min":"0.00","sd":"0.16","sensor":9},{"data_type":"pm1","value":"0.13","max":"2.00","min":"0.00","sd":"0.41","sensor":9},{"data_type":"pm10","value":"0.03","max":"1.00","min":"0.00","sd":"0.16","sensor":10},{"data_type":"pm2.5","value":"0.03","max":"1.00","min":"0.00","sd":"0.16","sensor":10},{"data_type":"pm1","value":"0.05","max":"1.00","min":"0.00","sd":"0.22","sensor":10},{"data_type":"pm10","value":"0.03","max":"1.00","min":"0.00","sd":"0.16","sensor":11},{"data_type":"pm2.5","value":"0.05","max":"1.00","min":"0.00","sd":"0.23","sensor":11},{"data_type":"pm1","value":"0.00","max":"0.00","min":"0.00","sd":"0.00","sensor":11},{"data_type":"pm10","value":"4.99","max":"5.43","min":"4.49","sd":"0.22","sensor":12},{"data_type":"pm2.5","value":"4366929.00","max":"4388928.50","min":"4349378.00","sd":"10196.31","sensor":12},{"data_type":"pm1","value":"1339382.12","max":"2175771.50","min":"1191556.25","sd":"248929.94","sensor":12},{"data_type":"pm10","value":"171.97","max":"173.00","min":"171.00","sd":"0.80","sensor":13},{"data_type":"pm2.5","value":"160.02","max":"161.00","min":"159.00","sd":"0.73","sensor":13},{"data_type":"pm1","value":"114.93","max":"117.00","min":"114.00","sd":"0.83","sensor":13},{"data_type":"pm10","value":"116.97","max":"117.00","min":"116.00","sd":"0.43","sensor":14},{"data_type":"pm2.5","value":"11.13","max":"12.00","min":"10.00","sd":"0.51","sensor":14},{"data_type":"pm1","value":"-2.20","max":"0.00","min":"-5.00","sd":"0.92","sensor":14},{"data_type":"noise","value":"15.00","max":"15.00","min":"15.00","sd":"0.00"},{"data_type":"illuminance","value":"48.00","max":"48.00","min":"48.00","sd":"0.00"},{"data_type":"irradiance","value":"21254.96","max":"21580.17","min":"21164.23","sd":"85.08"},{"data_type":"temperature","value":"27.75","max":"27.78","min":"27.71","sd":"0.11"},{"data_type":"humidity","value":"55.49","max":"55.79","min":"55.25","sd":"0.36"},{"data_type":"presure","value":"909.29","max":"909.34","min":"909.25","sd":"0.13"},{"data_type":"precipitation","value":"0.00","max":"0.00","min":"0.00","sd":"0.00"}]}
