{"timestamp":"2020-12-22T00:20:10Z","data":[{"data_type":"pm10","value":"16.14","max":"94.18","min":"1.12","sd":"20.05"},{"data_type":"pm2.5","value":"6.24","max":"10.76","min":"1.11","sd":"1.96"},{"data_type":"pm1","value":"2.26","max":"3.31","min":"0.71","sd":"0.51"},{"data_type":"pm10","value":"22.60","max":"31.00","min":"20.00","sd":"3.20","sensor":2},{"data_type":"pm2.5","value":"21.00","max":"23.00","min":"19.00","sd":"1.33","sensor":2},{"data_type":"pm1","value":"15.10","max":"16.00","min":"14.00","sd":"0.88","sensor":2},{"data_type":"pm10","value":"1530.20","max":"3213.00","min":"0.00","sd":"1528.62","sensor":5},{"data_type":"pm2.5","value":"783.70","max":"850.00","min":"713.00","sd":"44.85","sensor":5},{"data_type":"pm1","value":"107.10","max":"143.00","min":"88.00","sd":"16.27","sensor":5},{"data_type":"pm10","value":"8.90","max":"25.00","min":"4.00","sd":"6.14","sensor":6},{"data_type":"pm2.5","value":"2.10","max":"8.00","min":"0.00","sd":"2.23","sensor":6},{"data_type":"pm10","value":"1.92","max":"20.00","min":"0.00","sd":"3.67","sensor":7},{"data_type":"pm2.5","value":"24.79","max":"42.00","min":"9.00","sd":"6.54","sensor":7},{"data_type":"pm1","value":"3.51","max":"8.00","min":"0.00","sd":"1.96","sensor":7},{"data_type":"pm10","value":"1.26","max":"3.00","min":"0.00","sd":"0.91","sensor":8},{"data_type":"pm2.5","value":"0.31","max":"2.00","min":"0.00","sd":"0.57","sensor":8},{"data_type":"pm1","value":"0.21","max":"2.00","min":"0.00","sd":"0.47","sensor":8},{"data_type":"pm10","value":"0.05","max":"1.00","min":"0.00","sd":"0.23","sensor":9},{"data_type":"pm2.5","value":"0.00","max":"0.00","min":"0.00","sd":"0.00","sensor":9},{"data_type":"pm1","value":"0.05","max":"1.00","min":"0.00","sd":"0.23","sensor":9},{"data_type":"pm10","value":"0.00","max":"0.00","min":"0.00","sd":"0.00","sensor":10},{"data_type":"pm2.5","value":"0.03","max":"1.00","min":"0.00","sd":"0.16","sensor":10},{"data_type":"pm1","value":"0.00","max":"0.00","min":"0.00","sd":"0.00","sensor":10},{"data_type":"pm10","value":"0.00","max":"0.00","min":"0.00","sd":"0.00","sensor":11},{"data_type":"pm2.5","value":"0.00","max":"0.00","min":"0.00","sd":"0.00","sensor":11},{"data_type":"pm1","value":"0.05","max":"1.00","min":"0.00","sd":"0.22","sensor":11},{"data_type":"pm10","value":"5.03","max":"5.67","min":"4.11","sd":"0.44","sensor":12},{"data_type":"pm2.5","value":"4807615.00","max":"4820309.50","min":"4790559.00","sd":"8495.95","sensor":12},{"data_type":"pm1","value":"1204396.37","max":"1996872.25","min":"905155.81","sd":"230537.42","sensor":12},{"data_type":"pm10","value":"165.20","max":"168.00","min":"164.00","sd":"0.85","sensor":13},{"data_type":"pm2.5","value":"155.37","max":"157.00","min":"155.00","sd":"0.56","sensor":13},{"data_type":"pm1","value":"118.17","max":"119.00","min":"116.00","sd":"0.59","sensor":13},{"data_type":"pm10","value":"116.20","max":"117.00","min":"116.00","sd":"0.41","sensor":14},{"data_type":"pm2.5","value":"9.19","max":"11.00","min":"8.00","sd":"0.82","sensor":14},{"data_type":"pm1","value":"1.56","max":"3.00","min":"0.00","sd":"0.77","sensor":14},{"data_type":"noise","value":"15.00","max":"15.00","min":"15.00","sd":"0.00"},{"data_type":"illuminance","value":"49.00","max":"49.00","min":"49.00","sd":"0.00"},{"data_type":"irradiance","value":"0.00","max":"0.00","min":"0.00","sd":"0.00"},{"data_type":"temperature","value":"24.56","max":"24.56","min":"24.55","sd":"0.01"},{"data_type":"humidity","value":"69.98","max":"70.03","min":"69.96","sd":"0.02"},{"data_type":"presure","value":"906.81","max":"906.84","min":"906.78","sd":"0.01"},{"data_type":"rain","value":"0.00","max":"0.00","min":"0.00","sd":"0.00"},{"data_type":"precipitation","value":"0.00","max":"0.00","min":"0.00","sd":"0.00"}]}
