{"timestamp":"2020-12-22T17:05:15Z","data":[{"data_type":"pm10","value":"20.07","max":"113.97","min":"2.72","sd":"27.60"},{"data_type":"pm2.5","value":"5.08","max":"7.99","min":"2.13","sd":"1.50"},{"data_type":"pm1","value":"1.73","max":"2.46","min":"0.95","sd":"0.41"},{"data_type":"pm10","value":"17.68","max":"22.00","min":"15.00","sd":"1.41","sensor":2},{"data_type":"pm2.5","value":"16.41","max":"20.00","min":"14.00","sd":"1.48","sensor":2},{"data_type":"pm1","value":"11.54","max":"13.00","min":"9.00","sd":"1.16","sensor":2},{"data_type":"pm10","value":"1416.40","max":"2724.00","min":"0.00","sd":"1231.18","sensor":5},{"data_type":"pm2.5","value":"623.37","max":"705.00","min":"513.00","sd":"38.98","sensor":5},{"data_type":"pm1","value":"89.00","max":"110.00","min":"68.00","sd":"7.30","sensor":5},{"data_type":"pm10","value":"7.26","max":"13.00","min":"2.00","sd":"2.48","sensor":6},{"data_type":"pm2.5","value":"1.52","max":"3.00","min":"1.00","sd":"0.85","sensor":6},{"data_type":"pm10","value":"1.68","max":"8.00","min":"0.00","sd":"2.08","sensor":7},{"data_type":"pm2.5","value":"18.37","max":"28.00","min":"10.00","sd":"4.27","sensor":7},{"data_type":"pm1","value":"2.08","max":"5.00","min":"0.00","sd":"1.38","sensor":7},{"data_type":"pm10","value":"1.05","max":"4.00","min":"0.00","sd":"0.94","sensor":8},{"data_type":"pm2.5","value":"0.33","max":"1.00","min":"0.00","sd":"0.48","sensor":8},{"data_type":"pm1","value":"0.18","max":"1.00","min":"0.00","sd":"0.39","sensor":8},{"data_type":"pm10","value":"0.05","max":"1.00","min":"0.00","sd":"0.22","sensor":9},{"data_type":"pm2.5","value":"0.13","max":"1.00","min":"0.00","sd":"0.34","sensor":9},{"data_type":"pm10","value":"0.03","max":"1.00","min":"0.00","sd":"0.16","sensor":10},{"data_type":"pm2.5","value":"0.03","max":"1.00","min":"0.00","sd":"0.16","sensor":10},{"data_type":"pm1","value":"0.00","max":"0.00","min":"0.00","sd":"0.00","sensor":10},{"data_type":"pm10","value":"0.05","max":"1.00","min":"0.00","sd":"0.22","sensor":11},{"data_type":"pm2.5","value":"0.00","max":"0.00","min":"0.00","sd":"0.00","sensor":11},{"data_type":"pm1","value":"0.03","max":"1.00","min":"0.00","sd":"0.16","sensor":11},{"data_type":"pm10","value":"4.55","max":"5.30","min":"3.75","sd":"0.53","sensor":12},{"data_type":"pm2.5","value":"3718658.50","max":"3798647.75","min":"3686821.00","sd":"13502.88","sensor":12},{"data_type":"pm1","value":"1123151.75","max":"1907361.38","min":"994647.69","sd":"185657.75","sensor":12},{"data_type":"pm10","value":"180.23","max":"182.00","min":"177.00","sd":"1.19","sensor":13},{"data_type":"pm2.5","value":"165.27","max":"167.00","min":"162.00","sd":"0.98","sensor":13},{"data_type":"pm1","value":"113.50","max":"115.00","min":"112.00","sd":"0.78","sensor":13},{"data_type":"pm10","value":"116.97","max":"117.00","min":"116.00","sd":"0.18","sensor":14},{"data_type":"pm2.5","value":"14.17","max":"16.00","min":"12.00","sd":"1.15","sensor":14},{"data_type":"pm1","value":"-3.90","max":"0.00","min":"-7.00","sd":"0.96","sensor":14},{"data_type":"noise","value":"15.48","max":"21.96","min":"15.00","sd":"1.67"}]}
