{"timestamp":"2020-12-21T11:34:44Z","data":[{"data_type":"pm10","value":"16.98","max":"102.03","min":"2.26","sd":"22.99"},{"data_type":"pm2.5","value":"4.66","max":"9.45","min":"2.22","sd":"1.55"},{"data_type":"pm1","value":"1.54","max":"2.65","min":"0.84","sd":"0.39"},{"data_type":"pm10","value":"20.78","max":"24.00","min":"17.00","sd":"2.54","sensor":2},{"data_type":"pm2.5","value":"18.61","max":"20.00","min":"16.00","sd":"0.99","sensor":2},{"data_type":"pm1","value":"13.78","max":"15.00","min":"12.00","sd":"0.93","sensor":2},{"data_type":"pm10","value":"1435.56","max":"3075.00","min":"1.00","sd":"1432.48","sensor":5},{"data_type":"pm2.5","value":"732.44","max":"785.00","min":"653.00","sd":"55.20","sensor":5},{"data_type":"pm1","value":"99.44","max":"124.00","min":"86.00","sd":"14.60","sensor":5},{"data_type":"pm10","value":"6.44","max":"9.00","min":"4.00","sd":"1.67","sensor":6},{"data_type":"pm2.5","value":"3.33","max":"4.00","min":"1.00","sd":"1.12","sensor":6},{"data_type":"pm10","value":"1.64","max":"7.00","min":"0.00","sd":"1.60","sensor":7},{"data_type":"pm2.5","value":"15.77","max":"29.00","min":"5.00","sd":"4.57","sensor":7},{"data_type":"pm1","value":"1.89","max":"8.00","min":"0.00","sd":"1.19","sensor":7},{"data_type":"pm10","value":"0.63","max":"3.00","min":"0.00","sd":"0.93","sensor":8},{"data_type":"pm2.5","value":"0.24","max":"2.00","min":"0.00","sd":"0.67","sensor":8},{"data_type":"pm1","value":"0.24","max":"2.00","min":"0.00","sd":"0.67","sensor":8},{"data_type":"pm10","value":"0.06","max":"1.00","min":"0.00","sd":"0.50","sensor":9},{"data_type":"pm2.5","value":"0.05","max":"1.00","min":"0.00","sd":"0.47","sensor":9},{"data_type":"pm1","value":"0.07","max":"1.00","min":"0.00","sd":"0.50","sensor":9},{"data_type":"pm10","value":"0.00","max":"0.00","min":"0.00","sd":"0.00","sensor":10},{"data_type":"pm2.5","value":"0.00","max":"0.00","min":"0.00","sd":"0.00","sensor":10},{"data_type":"pm1","value":"0.01","max":"1.00","min":"0.00","sd":"0.28","sensor":10},{"data_type":"pm10","value":"0.01","max":"1.00","min":"0.00","sd":"0.29","sensor":11},{"data_type":"pm2.5","value":"0.00","max":"0.00","min":"0.00","sd":"0.00","sensor":11},{"data_type":"pm1","value":"0.01","max":"1.00","min":"0.00","sd":"0.29","sensor":11},{"data_type":"pm10","value":"4.53","max":"4.86","min":"3.87","sd":"0.22","sensor":12},{"data_type":"pm2.5","value":"3250623.75","max":"3256841.00","min":"3246865.75","sd":"2856.21","sensor":12},{"data_type":"pm1","value":"5370033.50","max":"6546228.50","min":"10328.47","sd":"2465056.50","sensor":12},{"data_type":"pm10","value":"182.29","max":"183.00","min":"181.00","sd":"0.71","sensor":13},{"data_type":"pm2.5","value":"164.43","max":"165.00","min":"164.00","sd":"0.71","sensor":13},{"data_type":"pm1","value":"116.47","max":"117.00","min":"116.00","sd":"0.71","sensor":13},{"data_type":"pm10","value":"115.20","max":"116.00","min":"115.00","sd":"0.63","sensor":14},{"data_type":"pm2.5","value":"17.35","max":"19.00","min":"16.00","sd":"0.84","sensor":14},{"data_type":"pm1","value":"0.65","max":"1.00","min":"0.00","sd":"0.70","sensor":14},{"data_type":"noise","value":"15.00","max":"15.00","min":"15.00","sd":"0.00"},{"data_type":"illuminance","value":"48.00","max":"48.00","min":"48.00","sd":"0.00"},{"data_type":"irradiance","value":"0.00","max":"0.00","min":"0.00","sd":"0.00"},{"data_type":"temperature","value":"26.15","max":"26.16","min":"26.14","sd":"0.01"},{"data_type":"humidity","value":"55.34","max":"55.37","min":"55.32","sd":"0.14"},{"data_type":"presure","value":"898.49","max":"898.51","min":"898.47","sd":"0.11"},{"data_type":"rain","value":"0.00","max":"0.00","min":"0.00","sd":"0.00"},{"data_type":"precipitation","value":"0.00","max":"0.00","min":"0.00","sd":"0.00"}]}
