{"timestamp":"2020-12-21T22:50:30Z","data":[{"data_type":"pm10","value":"21.40","max":"127.66","min":"2.21","sd":"25.40"},{"data_type":"pm2.5","value":"6.45","max":"10.69","min":"2.17","sd":"1.89"},{"data_type":"pm1","value":"2.08","max":"2.95","min":"1.20","sd":"0.46"},{"data_type":"pm10","value":"24.46","max":"26.00","min":"22.00","sd":"1.12","sensor":2},{"data_type":"pm2.5","value":"21.81","max":"23.00","min":"21.00","sd":"0.99","sensor":2},{"data_type":"pm1","value":"16.13","max":"17.00","min":"14.00","sd":"0.99","sensor":2},{"data_type":"pm10","value":"2144.67","max":"3369.00","min":"1.00","sd":"1516.46","sensor":5},{"data_type":"pm2.5","value":"802.67","max":"856.00","min":"748.00","sd":"35.81","sensor":5},{"data_type":"pm1","value":"116.56","max":"132.00","min":"95.00","sd":"12.56","sensor":5},{"data_type":"pm10","value":"8.78","max":"11.00","min":"5.00","sd":"2.05","sensor":6},{"data_type":"pm2.5","value":"3.44","max":"5.00","min":"1.00","sd":"1.42","sensor":6},{"data_type":"pm10","value":"0.90","max":"4.00","min":"0.00","sd":"1.21","sensor":7},{"data_type":"pm2.5","value":"21.49","max":"30.00","min":"12.00","sd":"5.61","sensor":7},{"data_type":"pm1","value":"2.97","max":"9.00","min":"0.00","sd":"2.05","sensor":7},{"data_type":"pm10","value":"0.97","max":"3.00","min":"0.00","sd":"1.01","sensor":8},{"data_type":"pm2.5","value":"0.23","max":"1.00","min":"0.00","sd":"0.43","sensor":8},{"data_type":"pm1","value":"0.36","max":"2.00","min":"0.00","sd":"0.58","sensor":8},{"data_type":"pm10","value":"0.21","max":"2.00","min":"0.00","sd":"0.47","sensor":9},{"data_type":"pm2.5","value":"0.18","max":"1.00","min":"0.00","sd":"0.39","sensor":9},{"data_type":"pm1","value":"0.08","max":"1.00","min":"0.00","sd":"0.27","sensor":9},{"data_type":"pm10","value":"0.03","max":"1.00","min":"0.00","sd":"0.16","sensor":10},{"data_type":"pm2.5","value":"0.03","max":"1.00","min":"0.00","sd":"0.16","sensor":10},{"data_type":"pm1","value":"0.00","max":"0.00","min":"0.00","sd":"0.00","sensor":10},{"data_type":"pm10","value":"0.00","max":"0.00","min":"0.00","sd":"0.00","sensor":11},{"data_type":"pm2.5","value":"0.00","max":"0.00","min":"0.00","sd":"0.00","sensor":11},{"data_type":"pm1","value":"0.03","max":"1.00","min":"0.00","sd":"0.16","sensor":11},{"data_type":"pm10","value":"4.70","max":"5.26","min":"4.03","sd":"0.29","sensor":12},{"data_type":"pm2.5","value":"4494196.00","max":"4501631.00","min":"4485881.00","sd":"3472.93","sensor":12},{"data_type":"pm1","value":"1142431.00","max":"1961069.12","min":"1030454.94","sd":"228729.53","sensor":12},{"data_type":"pm10","value":"168.20","max":"170.00","min":"166.00","sd":"0.85","sensor":13},{"data_type":"pm2.5","value":"157.40","max":"159.00","min":"156.00","sd":"0.62","sensor":13},{"data_type":"pm1","value":"117.43","max":"119.00","min":"117.00","sd":"0.57","sensor":13},{"data_type":"pm10","value":"116.00","max":"116.00","min":"116.00","sd":"0.00","sensor":14},{"data_type":"pm2.5","value":"10.13","max":"12.00","min":"9.00","sd":"0.73","sensor":14},{"data_type":"pm1","value":"1.10","max":"2.00","min":"0.00","sd":"0.48","sensor":14},{"data_type":"noise","value":"15.00","max":"15.00","min":"15.00","sd":"0.00"},{"data_type":"illuminance","value":"49.00","max":"49.00","min":"49.00","sd":"0.00"},{"data_type":"irradiance","value":"0.00","max":"0.00","min":"0.00","sd":"0.00"},{"data_type":"temperature","value":"25.59","max":"25.60","min":"25.59","sd":"0.07"},{"data_type":"humidity","value":"66.79","max":"66.84","min":"66.73","sd":"0.18"},{"data_type":"presure","value":"905.88","max":"905.90","min":"905.84","sd":"0.12"},{"data_type":"rain","value":"0.00","max":"0.00","min":"0.00","sd":"0.00"},{"data_type":"precipitation","value":"0.00","max":"0.00","min":"0.00","sd":"0.00"}]}
