{"timestamp":"2020-12-19T16:48:38Z","data":[{"data_type":"pm10","value":"26.30","max":"29.00","min":"24.00","sd":"1.18"},{"data_type":"pm2.5","value":"23.90","max":"26.00","min":"22.00","sd":"1.24"},{"data_type":"pm1","value":"16.53","max":"18.00","min":"15.00","sd":"0.86"},{"data_type":"pm10","value":"29.67","max":"34.00","min":"26.00","sd":"2.09","sensor":2},{"data_type":"pm2.5","value":"26.90","max":"30.00","min":"23.00","sd":"2.51","sensor":2},{"data_type":"pm1","value":"18.03","max":"20.00","min":"16.00","sd":"1.16","sensor":2},{"data_type":"pm10","value":"2909.80","max":"3090.00","min":"2742.00","sd":"100.11","sensor":3},{"data_type":"pm2.5","value":"895.47","max":"956.00","min":"834.00","sd":"34.52","sensor":3},{"data_type":"pm1","value":"152.00","max":"168.00","min":"138.00","sd":"9.88","sensor":3},{"data_type":"pm10","value":"6.93","max":"14.00","min":"2.00","sd":"3.63","sensor":4},{"data_type":"pm2.5","value":"3.60","max":"6.00","min":"0.00","sd":"1.85","sensor":4},{"data_type":"pm1","value":"2.13","max":"4.00","min":"0.00","sd":"1.28","sensor":4},{"data_type":"pm10","value":"1781.72","max":"3882.00","min":"0.00","sd":"1780.21","sensor":5},{"data_type":"pm2.5","value":"934.13","max":"1023.00","min":"865.00","sd":"40.18","sensor":5},{"data_type":"pm1","value":"174.47","max":"210.00","min":"141.00","sd":"23.67","sensor":5},{"data_type":"pm10","value":"15.50","max":"24.00","min":"8.00","sd":"3.81","sensor":6},{"data_type":"pm2.5","value":"2.27","max":"6.00","min":"0.00","sd":"1.46","sensor":6},{"data_type":"noise","value":"39.67","max":"78.81","min":"30.08","sd":"4.26"},{"data_type":"illuminance","value":"49.00","max":"49.00","min":"49.00","sd":"0.00"},{"data_type":"irradiance","value":"46.22","max":"46.22","min":"46.22","sd":"0.00"},{"data_type":"temperature","value":"25.16","max":"25.17","min":"25.14","sd":"0.01"},{"data_type":"humidity","value":"57.91","max":"57.97","min":"57.88","sd":"0.03"},{"data_type":"presure","value":"898.50","max":"898.55","min":"898.46","sd":"0.03"},{"data_type":"rain","value":"0.00","max":"0.00","min":"0.00","sd":"0.00"}]}
