{"timestamp":"2020-12-20T04:43:07Z","data":[{"data_type":"pm10","value":"40.10","max":"42.00","min":"37.00","sd":"1.03"},{"data_type":"pm2.5","value":"34.27","max":"36.00","min":"33.00","sd":"0.94"},{"data_type":"pm1","value":"20.63","max":"22.00","min":"19.00","sd":"0.81"},{"data_type":"pm10","value":"41.43","max":"46.00","min":"34.00","sd":"3.53","sensor":2},{"data_type":"pm2.5","value":"34.03","max":"37.00","min":"31.00","sd":"1.81","sensor":2},{"data_type":"pm1","value":"21.30","max":"23.00","min":"20.00","sd":"0.79","sensor":2},{"data_type":"pm10","value":"3833.60","max":"3990.00","min":"3660.00","sd":"102.91","sensor":3},{"data_type":"pm2.5","value":"1189.93","max":"1232.00","min":"1140.00","sd":"24.89","sensor":3},{"data_type":"pm1","value":"263.40","max":"290.00","min":"244.00","sd":"12.60","sensor":3},{"data_type":"pm10","value":"16.40","max":"22.00","min":"8.00","sd":"3.21","sensor":4},{"data_type":"pm2.5","value":"4.47","max":"8.00","min":"0.00","sd":"2.27","sensor":4},{"data_type":"pm1","value":"0.00","max":"0.00","min":"0.00","sd":"0.00","sensor":4},{"data_type":"pm10","value":"2329.07","max":"5151.00","min":"0.00","sd":"2327.96","sensor":5},{"data_type":"pm2.5","value":"1235.70","max":"1344.00","min":"1152.00","sd":"61.58","sensor":5},{"data_type":"pm1","value":"259.37","max":"299.00","min":"194.00","sd":"29.94","sensor":5},{"data_type":"pm10","value":"25.77","max":"38.00","min":"14.00","sd":"5.75","sensor":6},{"data_type":"pm2.5","value":"3.73","max":"8.00","min":"0.00","sd":"2.50","sensor":6},{"data_type":"noise","value":"250.65","max":"316.06","min":"193.66","sd":"13.22"},{"data_type":"illuminance","value":"52.83","max":"54.00","min":"52.00","sd":"0.62"},{"data_type":"irradiance","value":"0.00","max":"0.00","min":"0.00","sd":"0.00"},{"data_type":"temperature","value":"23.85","max":"23.85","min":"23.84","sd":"0.07"},{"data_type":"humidity","value":"72.58","max":"72.66","min":"72.53","sd":"0.20"},{"data_type":"presure","value":"907.88","max":"907.91","min":"907.86","sd":"0.02"},{"data_type":"rain","value":"0.00","max":"0.00","min":"0.00","sd":"0.00"}]}
