{"timestamp":"2021-01-02T15:03:23Z","data":[{"data_type":"noise","value":"36.50","max":"48.06","min":"32.40","sd":"2.15"},{"data_type":"illuminance","value":"2640.44","max":"2664.00","min":"2558.00","sd":"45.35"},{"data_type":"irradiance","value":"17700.68","max":"17744.32","min":"17651.89","sd":"29.54"},{"data_type":"temperature","value":"30.12","max":"30.13","min":"30.09","sd":"0.01"},{"data_type":"humidity","value":"47.20","max":"47.30","min":"47.04","sd":"0.08"},{"data_type":"presure","value":"909.39","max":"909.42","min":"909.36","sd":"0.02"},{"data_type":"rain","value":"0.00","max":"0.00","min":"0.00","sd":"0.00"},{"data_type":"precipitation","value":"0.00","max":"0.00","min":"0.00","sd":"0.00"}]}
