{"timestamp":"2021-01-02T15:50:56Z","data":[{"data_type":"noise","value":"35.35","max":"39.36","min":"32.98","sd":"1.24"},{"data_type":"illuminance","value":"2845.89","max":"2901.00","min":"2777.00","sd":"63.40"},{"data_type":"irradiance","value":"21138.56","max":"21256.66","min":"21071.80","sd":"55.42"},{"data_type":"temperature","value":"32.19","max":"32.21","min":"32.16","sd":"0.02"},{"data_type":"humidity","value":"41.57","max":"42.04","min":"41.30","sd":"0.24"},{"data_type":"presure","value":"908.76","max":"908.79","min":"908.73","sd":"0.13"},{"data_type":"rain","value":"0.00","max":"0.00","min":"0.00","sd":"0.00"},{"data_type":"precipitation","value":"0.00","max":"0.00","min":"0.00","sd":"0.00"},{"data_type":"voltage","value":"5.03","max":"5.04","min":"5.02","sd":"0.01"},{"data_type":"batery","value":"3.90","max":"3.91","min":"3.90","sd":"0.00"},{"data_type":"panel","value":"5.34","max":"5.34","min":"5.32","sd":"0.01"}]}
