{"timestamp":"2021-01-02T14:56:20Z","data":[{"data_type":"noise","value":"35.58","max":"39.94","min":"32.40","sd":"1.68"},{"data_type":"illuminance","value":"1938.44","max":"2664.00","min":"1417.00","sd":"489.39"},{"data_type":"irradiance","value":"9785.07","max":"17420.82","min":"4573.05","sd":"5286.92"},{"data_type":"temperature","value":"29.81","max":"29.83","min":"29.78","sd":"0.01"},{"data_type":"humidity","value":"49.83","max":"50.17","min":"49.38","sd":"0.20"},{"data_type":"presure","value":"909.46","max":"909.49","min":"909.41","sd":"0.02"},{"data_type":"rain","value":"0.00","max":"0.00","min":"0.00","sd":"0.00"},{"data_type":"precipitation","value":"0.00","max":"0.00","min":"0.00","sd":"0.00"}]}
