{"timestamp":"2021-01-02T13:29:51Z","data":[{"data_type":"pm10","value":"18.13","max":"20.00","min":"16.00","sd":"1.55"},{"data_type":"pm2.5","value":"17.67","max":"20.00","min":"15.00","sd":"1.88"},{"data_type":"pm1","value":"12.73","max":"14.00","min":"12.00","sd":"0.70"},{"data_type":"pm10","value":"13.27","max":"14.00","min":"12.00","sd":"0.88","sensor":2},{"data_type":"pm2.5","value":"12.80","max":"14.00","min":"12.00","sd":"0.94","sensor":2},{"data_type":"pm1","value":"10.53","max":"12.00","min":"9.00","sd":"0.99","sensor":2},{"data_type":"pm10","value":"2302.00","max":"2430.00","min":"2193.00","sd":"67.08","sensor":3},{"data_type":"pm2.5","value":"645.27","max":"684.00","min":"609.00","sd":"23.80","sensor":3},{"data_type":"pm1","value":"92.80","max":"100.00","min":"85.00","sd":"4.23","sensor":3},{"data_type":"pm10","value":"9.00","max":"18.00","min":"1.00","sd":"6.56","sensor":4},{"data_type":"pm2.5","value":"1.00","max":"2.00","min":"0.00","sd":"0.76","sensor":4},{"data_type":"pm1","value":"0.00","max":"0.00","min":"0.00","sd":"0.00","sensor":4},{"data_type":"pm10","value":"989.60","max":"2127.00","min":"0.00","sd":"989.62","sensor":5},{"data_type":"pm2.5","value":"555.87","max":"596.00","min":"522.00","sd":"25.70","sensor":5},{"data_type":"pm1","value":"65.93","max":"86.00","min":"46.00","sd":"13.20","sensor":5},{"data_type":"pm10","value":"2.40","max":"6.00","min":"0.00","sd":"2.20","sensor":6},{"data_type":"pm2.5","value":"0.47","max":"2.00","min":"0.00","sd":"0.74","sensor":6},{"data_type":"noise","value":"191.12","max":"271.97","min":"119.99","sd":"5.46"},{"data_type":"voltage","value":"0.00","max":"0.02","min":"0.00","sd":"0.06"},{"data_type":"batery","value":"3.74","max":"3.74","min":"3.73","sd":"0.05"},{"data_type":"panel","value":"0.05","max":"0.14","min":"0.05","sd":"0.11"}]}
